{
    "id": "797104090877919262",
    "name": "~ PHQ PROJECT",
    "description": "Paradox Roleplay FiveM Server",
    "icon": "a_8eae1cb4400788d2b6970bc83195c700",
    "splash": null,
    "discovery_splash": null,
    "banner": "29cc20ef695feff8050591a26c8dbeca",
    "approximate_presence_count": 1925,
    "approximate_member_count": 8649,
    "premium_subscription_count": 14,
    "preferred_locale": "el",
    "vanity_url_code": "phq-project-797104090877919262",
    "keywords": [
        "events",
        "fivem",
        "fivemrp",
        "giveaway",
        "giveaways",
        "gr",
        "greece",
        "greek",
        "roleplay",
        "rp"
    ],
    "features": [
        "COMMUNITY",
        "DISCOVERABLE",
        "ENABLED_DISCOVERABLE_BEFORE",
        "MEMBER_VERIFICATION_GATE_ENABLED",
        "PREVIEW_ENABLED"
    ],
    "partnered": false,
    "verified": false,
    "raw": {
        "id": "797104090877919262",
        "name": "~ PHQ PROJECT",
        "description": "Paradox Roleplay FiveM Server",
        "icon": "a_8eae1cb4400788d2b6970bc83195c700",
        "splash": null,
        "banner": "29cc20ef695feff8050591a26c8dbeca",
        "approximate_presence_count": 1925,
        "approximate_member_count": 8649,
        "premium_subscription_count": 14,
        "preferred_locale": "el",
        "auto_removed": false,
        "discovery_splash": null,
        "primary_category_id": 0,
        "vanity_url_code": "phq-project-797104090877919262",
        "is_published": false,
        "keywords": [
            "events",
            "fivem",
            "fivemrp",
            "giveaway",
            "giveaways",
            "gr",
            "greece",
            "greek",
            "roleplay",
            "rp"
        ],
        "features": [
            "COMMUNITY",
            "DISCOVERABLE",
            "ENABLED_DISCOVERABLE_BEFORE",
            "MEMBER_VERIFICATION_GATE_ENABLED",
            "PREVIEW_ENABLED"
        ],
        "categories": [
            {
                "id": 0,
                "is_primary": true,
                "name": "General",
                "name_localizations": null
            }
        ],
        "primary_category": {
            "id": 0,
            "is_primary": true,
            "name": "General",
            "name_localizations": null
        },
        "objectID": "797104090877919262",
        "_highlightResult": {
            "name": {
                "value": "~ PHQ PROJECT",
                "matchLevel": "none",
                "matchedWords": []
            },
            "description": {
                "value": "Paradox Roleplay FiveM Server",
                "matchLevel": "none",
                "matchedWords": []
            },
            "vanity_url_code": {
                "value": "phq-project-797104090877919262",
                "matchLevel": "none",
                "matchedWords": []
            },
            "keywords": [
                {
                    "value": "events",
                    "matchLevel": "none",
                    "matchedWords": []
                },
                {
                    "value": "fivem",
                    "matchLevel": "none",
                    "matchedWords": []
                },
                {
                    "value": "fivemrp",
                    "matchLevel": "none",
                    "matchedWords": []
                },
                {
                    "value": "giveaway",
                    "matchLevel": "none",
                    "matchedWords": []
                },
                {
                    "value": "giveaways",
                    "matchLevel": "none",
                    "matchedWords": []
                },
                {
                    "value": "gr",
                    "matchLevel": "none",
                    "matchedWords": []
                },
                {
                    "value": "greece",
                    "matchLevel": "none",
                    "matchedWords": []
                },
                {
                    "value": "greek",
                    "matchLevel": "none",
                    "matchedWords": []
                },
                {
                    "value": "roleplay",
                    "matchLevel": "none",
                    "matchedWords": []
                },
                {
                    "value": "rp",
                    "matchLevel": "none",
                    "matchedWords": []
                }
            ]
        }
    }
}